README.md
setup.cfg
setup.py
aiodisk/__init__.py
aiodisk/__main__.py
aiodisk/aiodisk.py
aiodisk/googledrive.py
aiodisk.egg-info/PKG-INFO
aiodisk.egg-info/SOURCES.txt
aiodisk.egg-info/dependency_links.txt
aiodisk.egg-info/entry_points.txt
aiodisk.egg-info/requires.txt
aiodisk.egg-info/top_level.txt