Metadata-Version: 1.1
Name: aiodisk
Version: 0.2
Summary: Access all cloud services in one script
Home-page: https://github.com/oguzbakir/AioDisk
Author: Oguz BAKIR
Author-email: worms298@gmail.com
License: UNKNOWN
Download-URL: https://github.com/oguzbakir/aiodisk/archive/0.1.tar.gz
Keywords: drive,mega,cloud,cloudaio
Platform: UNKNOWN
Classifier: Development Status :: 3 - Alpha
Classifier: Programming Language :: Python :: 3.6
